azuma/__init__.py
azuma/cli.py
azuma/exceptions.py
azuma/grammar.lark
azuma/matchers.py
azuma/types.py
azuma/validators.py
azuma/parsers/__init__.py
azuma/parsers/condition.py
azuma/parsers/detection.py
azuma/parsers/utils.py
azuma/schemas/__init__.py
azuma/schemas/detection.py
azuma/schemas/log_source.py
azuma/schemas/related.py
azuma/schemas/rule.py
azuma/schemas/rule_set.py
azuma/schemas/yaml_model.py
azuma-0.7.3.dist-info/METADATA
azuma-0.7.3.dist-info/WHEEL
azuma-0.7.3.dist-info/entry_points.txt
azuma-0.7.3.dist-info/licenses/LICENSE
azuma-0.7.3.dist-info/RECORD
