Metadata-Version: 2.4
Name: azuma
Version: 0.7.3
Summary: Yet another Sigma library for Python
Project-URL: Homepage, https://github.com/ninoseki/azuma
Project-URL: Repository, https://github.com/ninoseki/azuma
Author-email: Manabu Niseki <manabu.niseki@gmail.com>
License-Expression: MIT
License-File: LICENSE
Requires-Python: <4.0,>=3.10
Requires-Dist: lark[interegular]~=1.2
Requires-Dist: pydantic!=2.1.0,<3.0.0,>2.0.1
Requires-Dist: pyyaml~=6.0
Requires-Dist: regex>=2024.11.6
Requires-Dist: returns~=0.24
Requires-Dist: semver>=3.0.4
Requires-Dist: senkawa~=0.1
Requires-Dist: typer~=0.15
